vpt/__init__.py
vpt/app/__init__.py
vpt/app/context.py
vpt/app/empty.py
vpt/app/task.py
vpt/cmd_args.py
vpt/compile_tile_segmentation/__init__.py
vpt/compile_tile_segmentation/cmd_args.py
vpt/compile_tile_segmentation/main.py
vpt/compile_tile_segmentation/parameters.py
vpt/convert_geometry/__init__.py
vpt/convert_geometry/cmd_args.py
vpt/convert_geometry/converters/__init__.py
vpt/convert_geometry/converters/entity_id_generator.py
vpt/convert_geometry/converters/hdf5_converter.py
vpt/convert_geometry/converters/old_parquet_converter.py
vpt/convert_geometry/converters/qpath_geojson_converter.py
vpt/convert_geometry/factory.py
vpt/convert_geometry/main.py
vpt/convert_to_ome/__init__.py
vpt/convert_to_ome/cmd_args.py
vpt/convert_to_ome/main.py
vpt/convert_to_ome/main_rgb.py
vpt/convert_to_ome/rgb_cmd_args.py
vpt/convert_to_ome/tiffutils.py
vpt/derive_cell_metadata/__init__.py
vpt/derive_cell_metadata/__main__.py
vpt/derive_cell_metadata/cell_metadata.py
vpt/derive_cell_metadata/cmd_args.py
vpt/derive_cell_metadata/run_derive_cell_metadata.py
vpt/entity/__init__.py
vpt/entity/empty_resolver.py
vpt/entity/factory.py
vpt/entity/relationships.py
vpt/entity/resolver/__init__.py
vpt/entity/resolver/child_intersect_one_parent.py
vpt/entity/resolver/child_must_have_parent.py
vpt/entity/resolver/maximum_child_count.py
vpt/entity/resolver/minimum_child_count.py
vpt/entity/resolver/parent_must_cover_child.py
vpt/entity/resolver_base.py
vpt/entity/segmentation_results_worker.py
vpt/extract_image_patch/__init__.py
vpt/extract_image_patch/cmd_args.py
vpt/extract_image_patch/main.py
vpt/generate_segmentation_metrics/__init__.py
vpt/generate_segmentation_metrics/cluster_data.py
vpt/generate_segmentation_metrics/cmd_args.py
vpt/generate_segmentation_metrics/compute_metrics.py
vpt/generate_segmentation_metrics/distributions.py
vpt/generate_segmentation_metrics/distributions_utils.py
vpt/generate_segmentation_metrics/main.py
vpt/generate_segmentation_metrics/metrics_settings.py
vpt-1.3.0.dist-info/LICENSE.md
vpt-1.3.0.dist-info/METADATA
vpt-1.3.0.dist-info/WHEEL
vpt-1.3.0.dist-info/entry_points.txt
vpt-1.3.0.dist-info/RECORD
