Metadata-Version: 2.1
Name: vpt
Version: 1.3.0
Summary: Command line tool for highly parallelized processing of Vizgen data
Home-page: https://github.com/Vizgen/vizgen-postprocessing
License: Apache-2.0
Author: Vizgen
Author-email: techsupport@vizgen.com
Maintainer: Timothy Wiggin
Maintainer-email: timothy.wiggin@vizgen.com
Requires-Python: >=3.9,<3.11
Classifier: Development Status :: 5 - Production/Stable
Classifier: License :: OSI Approved :: Apache Software License
Classifier: Natural Language :: English
Classifier: Operating System :: MacOS :: MacOS X
Classifier: Operating System :: Microsoft :: Windows
Classifier: Operating System :: POSIX :: Linux
Classifier: Programming Language :: Python :: 3
Classifier: Programming Language :: Python :: 3.9
Classifier: Programming Language :: Python :: 3.10
Classifier: Topic :: Scientific/Engineering :: Bio-Informatics
Classifier: Topic :: Scientific/Engineering :: Image Processing
Provides-Extra: all
Provides-Extra: cellpose
Provides-Extra: watershed
Requires-Dist: boto3 (>=1.17)
Requires-Dist: dask (>=2023.2.0)
Requires-Dist: distributed (>=2023.2.0)
Requires-Dist: fastparquet (==2023.10.1)
Requires-Dist: fsspec (==2024.2.0)
Requires-Dist: gcsfs (==2024.2.0)
Requires-Dist: geopandas (>=0.13.2,<=0.14.4)
Requires-Dist: h5py (>=3.7.0)
Requires-Dist: ipykernel
Requires-Dist: jinja2 (==3.1.3)
Requires-Dist: kaleido (==0.1.0) ; sys_platform == "darwin"
Requires-Dist: kaleido (==0.1.0) ; sys_platform == "linux"
Requires-Dist: kaleido (==0.1post1) ; sys_platform == "win32"
Requires-Dist: leidenalg (>=0.10.1,<0.11.0)
Requires-Dist: matplotlib (<=3.7.0)
Requires-Dist: numpy (>=1.24.3)
Requires-Dist: pandas (>=2.0.3)
Requires-Dist: plotly (>=5.17.0,<6.0.0)
Requires-Dist: pretty-html-table (>=0.9.16,<0.10.0)
Requires-Dist: pyarrow (>=8.0.0,<14.0.0)
Requires-Dist: python-dotenv (>=0.20.0)
Requires-Dist: pyvips (>=2.2.1)
Requires-Dist: rasterio (>=1.3.0,<1.3.6)
Requires-Dist: s3fs (==2024.2.0)
Requires-Dist: scanpy (==1.9.3)
Requires-Dist: scipy (>=1.8.1)
Requires-Dist: shapely (>=2.0.0)
Requires-Dist: torch (>=2.0.0,!=2.0.1,!=2.1.0)
Requires-Dist: vpt-segmentation-packing (>=1.0.0)
Requires-Dist: vpt_core (>=1.2.0)
Requires-Dist: vpt_plugin_cellpose (>=1.0.0) ; extra == "cellpose" or extra == "all"
Requires-Dist: vpt_plugin_watershed (>=1.0.0) ; extra == "watershed" or extra == "all"
Requires-Dist: wrapt_timeout_decorator (>=1.5.1)
Project-URL: Documentation, https://vizgen.github.io/vizgen-postprocessing/
Project-URL: Repository, https://github.com/Vizgen/vizgen-postprocessing
